xxlSearch/__init__.py
xxlSearch/main.py
xxlSearch-0.1.0.dist-info/METADATA
xxlSearch-0.1.0.dist-info/WHEEL
xxlSearch-0.1.0.dist-info/entry_points.txt
xxlSearch-0.1.0.dist-info/top_level.txt
xxlSearch-0.1.0.dist-info/RECORD
